scbw_mq/__init__.py
scbw_mq/rabbitmq_consumer.py
scbw_mq/utils.py
scbw_mq/parser/__init__.py
scbw_mq/parser/cli.py
scbw_mq/parser/consumer.py
scbw_mq/parser/message.py
scbw_mq/parser/producer.py
scbw_mq/tournament/__init__.py
scbw_mq/tournament/cli.py
scbw_mq/tournament/consumer.py
scbw_mq/tournament/dump.py
scbw_mq/tournament/message.py
scbw_mq/tournament/producer.py
scbw_mq/tournament/benchmark/__init__.py
scbw_mq/tournament/benchmark/factory.py
scbw_mq/tournament/benchmark/plots.py
scbw_mq/tournament/benchmark/stats.py
scbw_mq/tournament/benchmark/storage.py
scbw_mq-0.2.2.dist-info/DESCRIPTION.rst
scbw_mq-0.2.2.dist-info/METADATA
scbw_mq-0.2.2.dist-info/RECORD
scbw_mq-0.2.2.dist-info/WHEEL
scbw_mq-0.2.2.dist-info/entry_points.txt
scbw_mq-0.2.2.dist-info/metadata.json
scbw_mq-0.2.2.dist-info/top_level.txt
tournament/__init__.py
tournament/application.py
tournament/calc_elo.py
tournament/calc_win_table.py
tournament/cli.py
tournament/client.py
tournament/consumer.py
tournament/message.py
tournament/play.py
tournament/producer.py
tournament/rabbitmq_consumer.py
tournament/responses.py
tournament/results2csv.py
tournament/utils.py
